README.md
setup.py
prisoners_problem/__init__.py
prisoners_problem/simulate.py
prisoners_problem/simulate_fast.cpp
prisoners_problem/simulate_fast.py
prisoners_problem/viz.py
prisoners_problem.egg-info/PKG-INFO
prisoners_problem.egg-info/SOURCES.txt
prisoners_problem.egg-info/dependency_links.txt
prisoners_problem.egg-info/requires.txt
prisoners_problem.egg-info/top_level.txt