Metadata-Version: 2.1
Name: prisoners-problem
Version: 0.0.10
Summary: Simulate the 100 prisoners problem.
Home-page: https://github.com/tekknolagi/100prisoners
Author: Maxwell Bernstein
Author-email: python@bernsteinbear.com
License: UNKNOWN
Platform: UNKNOWN
Classifier: Programming Language :: Python :: 3
Classifier: License :: OSI Approved :: MIT License
Classifier: Operating System :: OS Independent
